garf/community/google/youtube/__init__.py
garf/community/google/youtube/api_clients.py
garf/community/google/youtube/exceptions.py
garf/community/google/youtube/query_editor.py
garf/community/google/youtube/report_fetcher.py
garf/community/google/youtube/simulator.py
garf/community/google/youtube/telemetry.py
garf/community/google/youtube/builtins/__init__.py
garf/community/google/youtube/builtins/channel_videos.py
garf_youtube_data_api/__init__.py
garf_youtube_data_api/api_clients.py
garf_youtube_data_api/exceptions.py
garf_youtube_data_api/query_editor.py
garf_youtube_data_api/report_fetcher.py
garf_youtube_data_api/simulator.py
garf_youtube_data_api/telemetry.py
garf_youtube_data_api/builtins/__init__.py
garf_youtube_data_api/builtins/channel_videos.py
garf_youtube_reporting_api/__init__.py
garf_youtube_reporting_api/api_clients.py
garf_youtube_reporting_api/exceptions.py
garf_youtube_reporting_api/query_editor.py
garf_youtube_reporting_api/report_fetcher.py
garf_youtube-1.0.0.dist-info/METADATA
garf_youtube-1.0.0.dist-info/WHEEL
garf_youtube-1.0.0.dist-info/entry_points.txt
garf_youtube-1.0.0.dist-info/top_level.txt
garf_youtube-1.0.0.dist-info/RECORD
