Metadata-Version: 2.4
Name: garf-youtube
Version: 1.0.0
Summary: Garf connector to YouTube APIs
Author-email: Andrei Markin <amarkin@google.com>, "Google Inc. (gTech gPS CSE team)" <no-reply@google.com>
License: Apache 2.0
Classifier: Development Status :: 4 - Beta
Classifier: Programming Language :: Python
Requires-Python: >=3.9
Requires-Dist: garf-core[pandas]>=1.0.0
Requires-Dist: garf-io>=1.0.0
Requires-Dist: google-api-python-client
Provides-Extra: test
Requires-Dist: pytest; extra == "test"
Requires-Dist: pytest-cov; extra == "test"
Requires-Dist: pytest-mock; extra == "test"
Requires-Dist: python-dotenv; extra == "test"
